examples/__init__.py
examples/coco_looking/__init__.py
examples/coco_looking/setup.py
examples/coco_looking/collectibles/__init__.py
examples/coco_looking/collectibles/defaults.py
examples/coco_looking/criterions/__init__.py
examples/coco_looking/criterions/defaults.py
examples/coco_looking/data_builders/__init__.py
examples/coco_looking/data_builders/defaults.py
examples/coco_looking/datasets/__init__.py
examples/coco_looking/datasets/defaults.py
examples/coco_looking/experiments/__init__.py
examples/coco_looking/experiments/defaults.py
examples/coco_looking/metrics/__init__.py
examples/coco_looking/metrics/defaults.py
examples/coco_looking/models/__init__.py
examples/coco_looking/models/alexnet.py
examples/coco_looking/models/custom_cnn.py
examples/coco_looking/models/custom_conv.py
examples/coco_looking/models/defaults.py
examples/coco_looking/models/facenet.py
examples/coco_looking/models/inception.py
examples/coco_looking/models/resnet.py
examples/coco_looking/optimizers/__init__.py
examples/coco_looking/optimizers/adam.py
examples/coco_looking/optimizers/defaults.py
examples/coco_looking/writers/__init__.py
examples/coco_looking/writers/defaults.py
examples/minerl/__init__.py
examples/minerl/setup.py
examples/minerl/collectibles/__init__.py
examples/minerl/collectibles/defaults.py
examples/minerl/criterions/__init__.py
examples/minerl/criterions/defaults.py
examples/minerl/data_builders/__init__.py
examples/minerl/data_builders/defaults.py
examples/minerl/datasets/__init__.py
examples/minerl/datasets/defaults.py
examples/minerl/envs/__init__.py
examples/minerl/envs/defaults.py
examples/minerl/envs/env_client.py
examples/minerl/envs/env_server.py
examples/minerl/experiments/__init__.py
examples/minerl/experiments/defaults.py
examples/minerl/metrics/__init__.py
examples/minerl/metrics/defaults.py
examples/minerl/models/__init__.py
examples/minerl/models/defaults.py
examples/minerl/optimizers/__init__.py
examples/minerl/optimizers/defaults.py
torch_lighter-0.2.26.dist-info/METADATA
torch_lighter-0.2.26.dist-info/WHEEL
torch_lighter-0.2.26.dist-info/top_level.txt
torch_lighter-0.2.26.dist-info/zip-safe
torch_lighter-0.2.26.dist-info/RECORD
