Metadata-Version: 2.1
Name: torch-lighter
Version: 0.2.26
Summary: Lightweight extension for torch to speed-up prototyping.
Home-page: https://github.com/Xpitfire/lighter
Author: Marius-Constantin Dinu
Author-email: dinu.marius-constantin@hotmail.com
License: UNKNOWN
Platform: UNKNOWN
Classifier: Programming Language :: Python :: 3
Classifier: License :: OSI Approved :: BSD License
Classifier: Operating System :: OS Independent
Requires-Dist: ffmpeg
Requires-Dist: natsort
Requires-Dist: numpy
Requires-Dist: tqdm
Requires-Dist: torch
Requires-Dist: torchvision
Requires-Dist: tensorboard
Requires-Dist: coloredlogs
Requires-Dist: petname
Requires-Dist: pandas
Requires-Dist: setproctitle
Requires-Dist: multiprocess
Requires-Dist: python-box
